featureclass/__init__.py
featureclass/cached_property.py
featureclass/core.py
featureclass/py.typed
featureclass-0.3.0.dist-info/LICENSE
featureclass-0.3.0.dist-info/WHEEL
featureclass-0.3.0.dist-info/METADATA
featureclass-0.3.0.dist-info/RECORD
